{
  "disposition": {
    "name": "What was the Overall Outcome?",
    "answers": {
      "2": {
        "value": "answering machine"
      },
      "3": {
        "value": "not interested"
      },
      "4": {
        "value": "meaningful conversation",
        "next": "loan_support"
      },
      "5": {
        "value": "can’t talk now, call back later"
      },
      "6": {
        "value": "do not call"
      },
      "7": {
        "value": "no answer"
      },
      "8": {
        "value": "wrong number"
      }
    }
  },
  "loan_support": {
    "name": "Do they support the Loan?",
    "answers": {
      "2": {
        "value": "supports the loan"
      },
      "3": {
        "value": "does not support the loan",
        "next": "prefered_spending_priority"
      },
      "4": {
        "value": "unsure about support for the loan",
        "next": "prefered_spending_priority"
      }
    }
  },
  "prefered_spending_priority": {
    "name": "What’s their prefered spending priority?",
    "answers": {
      "2": {
        "value": "healthcare",
        "next": "coalition_support"
      },
      "3": {
        "value": "education",
        "next": "coalition_support"
      },
      "4": {
        "value": "job creation",
        "next": "coalition_support"
      },
      "5": {
        "value": "local infrastructure",
        "next": "coalition_support"
      },
      "6": {
        "value": "disaster relief to rebuild infrastructure in queensland",
        "next": "coalition_support"
      },
      "7": {
        "value": "other",
        "next": "coalition_support"
      }
    }
  },
  "coalition_support": {
    "name": "Will it influence their support for the coalition?",
    "answers": {
      "2": {
        "value": "would influence their support for the coalition",
        "next": "voter_id"
      },
      "3": {
        "value": "would not influence their support for the coalition",
        "next": "voter_id"
      },
      "4": {
        "value": "may influence their support for the coalition",
        "next": "voter_id"
      },
      "5": {
        "value": "would not say",
        "next": "voter_id"
      }
    }
  },
  "voter_id": {
    "name": "Who did they vote for in the last federal election?",
    "answers": {
      "2": {
        "value": "LNP and Liberals",
        "next": "action"
      },
      "3": {
        "value": "Labour",
        "next": "action"
      },
      "4": {
        "value": "Greens",
        "next": "action"
      },
      "5": {
        "value": "Hanson",
        "next": "action"
      },
      "6": {
        "value": "Other",
        "next": "action"
      },
      "7": {
        "value": "Did not say",
        "next": "action"
      }
    }
  },
  "action": {
    "name": "What action did they agree to take?",
    "type": "SMS",
    "answers": {
      "2": {
        "value": "will call member of parliament",
        "deliver": true,
        "content": "Hi, thanks for taking action on this important issue! David Coleman’s number is 9771 3400. Ideally, call during office hours, so that your message can’t be ignored. Tell the person that you speak to that you live in the Forde electorate, your views on  the $1 billion government funding for the Adani coal mine, and that you would like to know what David Coleman’s position is on this issue."
      },
      "3": {
        "value": "may call member of parliament",
        "deliver": true,
        "content": "Hi, thanks for talking to me tonight! Remember David Coleman is your representative and should be working for you. If you’re able to give his office a quick call on 9771 3400, that would be great! Just tell the person that you speak to that you live in the Forde electorate, you are opposed to the $1 billion government funding for the Adani coal mine, and you would like to know what David Coleman’s position is on this issue."
      },
      "4": {
        "value": "will email member of parliament",
        "deliver": true,
        "content": "Hi, thanks for taking action on this important issue! David Coleman’s email is david.coleman.mp@aph.gov.au. Here’s a sample message: (Dear Mr Coleman, I live in the Forde electorate and I am opposed to the $1 billion NAIF funding for the Adani coal mine. Could you please tell me what your position on this issue is?)"
      },
      "5": {
        "value": "may email member of parliament",
        "deliver": true,
        "content": "Hi, thanks for talking to me tonight! Remember David Coleman is your representative and should be working for you. If you could send a quick email him, that would be great! His email is david.coleman.mp@aph.gov.au. Here’s a sample message: (Dear Mr Coleman, I live in the Forde electorate and I am opposed to the $1 billion NAIF funding for the Adani coal mine. Could you please tell me what your position on this issue is?)"
      },
      "6": {
        "value": "will not take action",
        "deliver": false
      }
    }
  }
}